groupby_lib/__init__.py
groupby_lib/emas.py
groupby_lib/extensions.py
groupby_lib/nanops.py
groupby_lib/util.py
groupby_lib/groupby/__init__.py
groupby_lib/groupby/api.py
groupby_lib/groupby/core.py
groupby_lib/groupby/factorization.py
groupby_lib/groupby/monkey_patch.py
groupby_lib/groupby/numba.py
groupby_lib/plotting/__init__.py
groupby_lib/plotting/group_scatter.py
groupby_lib-0.6.0.dist-info/licenses/LICENSE
groupby_lib-0.6.0.dist-info/METADATA
groupby_lib-0.6.0.dist-info/WHEEL
groupby_lib-0.6.0.dist-info/top_level.txt
groupby_lib-0.6.0.dist-info/RECORD
