Metadata-Version: 2.4
Name: groupby-lib
Version: 0.6.0
Summary: High-performance extension package for pandas with fast groupby operations
Home-page: https://github.com/eoincondron/groupby-lib
Author: Eoin Condron
Author-email: Your Name <your.email@example.com>
License: MIT
Project-URL: Homepage, https://github.com/eoincondron/groupby-lib
Project-URL: Bug Reports, https://github.com/eoincondron/groupby-lib/issues
Project-URL: Source, https://github.com/eoincondron/groupby-lib
Project-URL: Documentation, https://github.com/eoincondron/groupby-lib/blob/main/README.md
Keywords: pandas,groupby,performance,numba,numpy,data-analysis
Classifier: Development Status :: 3 - Alpha
Classifier: Intended Audience :: Developers
Classifier: Intended Audience :: Science/Research
Classifier: License :: OSI Approved :: MIT License
Classifier: Operating System :: OS Independent
Classifier: Programming Language :: Python :: 3.10
Classifier: Programming Language :: Python :: 3.11
Classifier: Programming Language :: Python :: 3.12
Classifier: Programming Language :: Python :: 3.13
Classifier: Topic :: Scientific/Engineering
Classifier: Topic :: Software Development :: Libraries :: Python Modules
Requires-Python: >=3.10
License-File: LICENSE
Requires-Dist: numpy>=1.19.0
Requires-Dist: pandas>=1.3.0
Requires-Dist: numba>=0.56.0
Requires-Dist: polars>=0.15.0
Requires-Dist: pyarrow>=1.0.0
Provides-Extra: dev
Requires-Dist: pytest>=6.0; extra == "dev"
Requires-Dist: pytest-xdist; extra == "dev"
Requires-Dist: black; extra == "dev"
Requires-Dist: flake8; extra == "dev"
Requires-Dist: isort; extra == "dev"
Requires-Dist: mypy; extra == "dev"
Requires-Dist: bandit; extra == "dev"
Requires-Dist: safety; extra == "dev"
Provides-Extra: plotting
Requires-Dist: matplotlib>=3.0.0; extra == "plotting"
Requires-Dist: seaborn>=0.11.0; extra == "plotting"
Provides-Extra: test
Requires-Dist: pytest>=6.0; extra == "test"
Requires-Dist: pytest-xdist; extra == "test"
Dynamic: author
Dynamic: home-page
Dynamic: license-file
Dynamic: requires-python
